aitkens/__init__.py
aitkens-0.1.0.dist-info/METADATA
aitkens-0.1.0.dist-info/WHEEL
aitkens-0.1.0.dist-info/top_level.txt
aitkens-0.1.0.dist-info/RECORD
