Metadata-Version: 2.1
Name: aitkens
Version: 0.1.0
Summary: Aitken's delta-squared acceleration
Home-page: https://github.com/jftsang/aitkens
Author: J. M. F. Tsang
Author-email: j.m.f.tsang@cantab.net
License: CC BY 4.0
Platform: UNKNOWN
Requires-Dist: numpy
Provides-Extra: develop
Requires-Dist: hypothesis ; extra == 'develop'
